apr_detector/__init__.py
apr_detector/__main__.py
apr_detector/cli.py
apr_detector/config/__init__.py
apr_detector/config/config.py
apr_detector/core/__init__.py
apr_detector/core/complement.py
apr_detector/core/detector.py
apr_detector/core/exceptions.py
apr_detector/core/scoring.py
apr_detector/core/sequence.py
apr_detector/core/tract.py
apr_detector-0.1.0.dist-info/licenses/LICENSE
apr_detector-0.1.0.dist-info/METADATA
apr_detector-0.1.0.dist-info/WHEEL
apr_detector-0.1.0.dist-info/entry_points.txt
apr_detector-0.1.0.dist-info/top_level.txt
apr_detector-0.1.0.dist-info/RECORD
