Metadata-Version: 2.4
Name: apr-detector
Version: 0.1.0
Summary: High-throughput pipeline for detecting A-phased repeats (APRs) in large genomes.
Author-email: Hamza Mohammed <mohammed-hamza@uiowa.edu>, "Josep Comeron, PhD" <josep-comeron@uiowa.edu>
License-Expression: MIT
Project-URL: Homepage, https://github.com/hamza-mohammed99/apr-detector
Project-URL: Issues, https://github.com/hamza-mohammed99/apr-detector/issues
Classifier: Programming Language :: Python :: 3
Classifier: Programming Language :: Python :: 3.9
Classifier: Programming Language :: Python :: 3.10
Classifier: Programming Language :: Python :: 3.11
Classifier: Programming Language :: Python :: 3.12
Classifier: Operating System :: OS Independent
Requires-Python: <3.13,>=3.9
License-File: LICENSE
Provides-Extra: test
Requires-Dist: pytest; extra == "test"
Dynamic: license-file
